odoo10_addon_l10n_br_account_product-10.0.1.0.0.99.dev56-nspkg.pth
odoo/addons/l10n_br_account_product/README.rst
odoo/addons/l10n_br_account_product/__init__.py
odoo/addons/l10n_br_account_product/__manifest__.py
odoo/addons/l10n_br_account_product/data/ir_cron.xml
odoo/addons/l10n_br_account_product/data/l10n_br_account.fiscal.document.csv
odoo/addons/l10n_br_account_product/data/l10n_br_account_data.xml
odoo/addons/l10n_br_account_product/data/l10n_br_account_product.cfop.csv
odoo/addons/l10n_br_account_product/data/l10n_br_account_product_cst_data.xml
odoo/addons/l10n_br_account_product/data/l10n_br_account_product_data.xml
odoo/addons/l10n_br_account_product/data/l10n_br_account_product_sequence.xml
odoo/addons/l10n_br_account_product/data/l10n_br_tax.icms_partition.csv
odoo/addons/l10n_br_account_product/demo/account_fiscal_position_rule_demo.xml
odoo/addons/l10n_br_account_product/demo/account_invoice_demo.xml
odoo/addons/l10n_br_account_product/demo/account_invoice_demo.yml
odoo/addons/l10n_br_account_product/demo/account_nfe_demo.xml
odoo/addons/l10n_br_account_product/demo/account_nfe_demo.yml
odoo/addons/l10n_br_account_product/demo/account_nfe_supplier_demo.xml
odoo/addons/l10n_br_account_product/demo/account_tax_demo.xml
odoo/addons/l10n_br_account_product/demo/base_demo.xml
odoo/addons/l10n_br_account_product/demo/l10n_br_account_product_demo.xml
odoo/addons/l10n_br_account_product/demo/product_demo.xml
odoo/addons/l10n_br_account_product/demo/product_taxes.yml
odoo/addons/l10n_br_account_product/i18n/l10n_br_account_product.pot
odoo/addons/l10n_br_account_product/migrations/8.0.2.0.0/pre-migration.py
odoo/addons/l10n_br_account_product/models/__init__.py
odoo/addons/l10n_br_account_product/models/account_fiscal_position.py
odoo/addons/l10n_br_account_product/models/account_fiscal_position_template.py
odoo/addons/l10n_br_account_product/models/account_invoice.py
odoo/addons/l10n_br_account_product/models/account_invoice_line.py
odoo10_addon_l10n_br_account_product-10.0.1.0.0.99.dev56.dist-info/METADATA
odoo10_addon_l10n_br_account_product-10.0.1.0.0.99.dev56.dist-info/WHEEL
odoo10_addon_l10n_br_account_product-10.0.1.0.0.99.dev56.dist-info/namespace_packages.txt
odoo10_addon_l10n_br_account_product-10.0.1.0.0.99.dev56.dist-info/top_level.txt
odoo10_addon_l10n_br_account_product-10.0.1.0.0.99.dev56.dist-info/RECORD
