Metadata-Version: 2.1
Name: odoo10-addon-l10n-br-account-product
Version: 10.0.1.0.0.99.dev56
Summary: Brazilian Localization Account Product
Home-page: http://odoo-brasil.org
Author: Akretion, Odoo Community Association (OCA)
Author-email: support@odoo-community.org
License: AGPL-3
Platform: UNKNOWN
Classifier: Programming Language :: Python
Classifier: Framework :: Odoo
Classifier: License :: OSI Approved :: GNU Affero General Public License v3
Requires-Python: ~=2.7
Requires-Dist: odoo10-addon-account-payment-mode
Requires-Dist: odoo10-addon-account-payment-partner
Requires-Dist: odoo10-addon-account-product-fiscal-classification
Requires-Dist: odoo10-addon-l10n-br-account
Requires-Dist: odoo (<10.1dev,>=10.0)
